{
    "default": {
        "formatOptions": {
            "snippetInterface": "async-await"
        },
        
        "paths": [
            "src/test/features/webDesktop/accueil/Accueil_login.feature"
        ],
        "publishQuiet": true,
        "dryRun": false,
        "require": [
            "src/test/steps/commun/*.js",
            "src/hook/hook.js"
        ],  

        "format": [
            "progress-bar",
            "json:reporting/rapports/cucumber-reports.json"
        ]
    }  
}